fluxsession/__init__.py
fluxsession/session.py
fluxsession-0.1.5.dist-info/METADATA
fluxsession-0.1.5.dist-info/WHEEL
fluxsession-0.1.5.dist-info/RECORD
