Metadata-Version: 2.1
Name: fluxsession
Version: 0.1.5
Summary: A Session converter for Telegram unoffical client.
Author: Md. Hasibul Kabir
Author-email: 46620128+HasibulKabir@users.noreply.github.com
Requires-Python: >=3.8
Classifier: Programming Language :: Python :: 3
Classifier: Programming Language :: Python :: 3.8
Classifier: Programming Language :: Python :: 3.9
Classifier: Programming Language :: Python :: 3.10
Classifier: Programming Language :: Python :: 3.11
Classifier: Programming Language :: Python :: 3.12
Requires-Dist: pydantic (>=2.0)
Requires-Dist: telethon (>=1.25.4)
